Metadata-Version: 2.4
Name: underscores
Version: 0.0.3
Summary: _ allows you to write Python code using only _.
Author: Lemonyte
License-Expression: MIT
Project-URL: Repository, https://github.com/lemonyte/_
Keywords: _,underscore,encoding,joke
Classifier: Development Status :: 3 - Alpha
Classifier: Intended Audience :: Developers
Classifier: Operating System :: OS Independent
Classifier: Programming Language :: Python :: 3
Classifier: Topic :: Utilities
Requires-Python: >=3.9
License-File: LICENSE.txt
Dynamic: license-file
